{
  "type": "FeatureCollection",
  "name": "02_18_UTOPIAS",
  "crs": {
    "type": "name",
    "properties": {
      "name": "urn:ogc:def:crs:OGC:1.3:CRS84"
    }
  },
  "features": [
    {
      "type": "Feature",
      "properties": {
        "ID": null,
        "EJE": null,
        "PROGRAMA": "UTOPIA",
        "FRENTE": "UTOPIA CUAUHTLICALLI"
      },
      "geometry": {
        "type": "Point",
        "coordinates": [-99.10978859, 19.36677093]
      }
    },
    {
      "type": "Feature",
      "properties": {
        "ID": null,
        "EJE": null,
        "PROGRAMA": "UTOPIA",
        "FRENTE": "UTOPIA ATZINTLI"
      },
      "geometry": {
        "type": "Point",
        "coordinates": [-99.01922237, 19.3448606]
      }
    },
    {
      "type": "Feature",
      "properties": {
        "ID": null,
        "EJE": null,
        "PROGRAMA": "UTOPIA",
        "FRENTE": "UTOPIA MEYEHUALCO"
      },
      "geometry": {
        "type": "Point",
        "coordinates": [-99.04852264, 19.34483653]
      }
    },
    {
      "type": "Feature",
      "properties": {
        "ID": null,
        "EJE": null,
        "PROGRAMA": "UTOPIA",
        "FRENTE": "UTOPIA CASCADA"
      },
      "geometry": {
        "type": "Point",
        "coordinates": [-99.0251827, 19.38199832]
      }
    },
    {
      "type": "Feature",
      "properties": {
        "ID": null,
        "EJE": null,
        "PROGRAMA": "UTOPIA",
        "FRENTE": "UTOPIA QUETZALCOATL"
      },
      "geometry": {
        "type": "Point",
        "coordinates": [-99.0431262, 19.32715483]
      }
    },
    {
      "type": "Feature",
      "properties": {
        "ID": null,
        "EJE": null,
        "PROGRAMA": "UTOPIA",
        "FRENTE": "UTOPIA PAPALOTL"
      },
      "geometry": {
        "type": "Point",
        "coordinates": [-99.03231235, 19.34215116]
      }
    }
  ]
}
